aiographite/__init__.py
aiographite/aiographite.py
aiographite/graphite_encoder.py
aiographite/protocol.py
aiographite-0.1.9.dist-info/DESCRIPTION.rst
aiographite-0.1.9.dist-info/METADATA
aiographite-0.1.9.dist-info/RECORD
aiographite-0.1.9.dist-info/WHEEL
aiographite-0.1.9.dist-info/metadata.json
aiographite-0.1.9.dist-info/top_level.txt
tests/__init__.py
tests/conftest.py
tests/test_graphite_encoder.py
tests/test_graphite_send.py
