Metadata-Version: 2.0
Name: aiographite
Version: 0.1.9
Summary: UNKNOWN
Home-page: UNKNOWN
Author: Yun Xu
Author-email: yunx@zillowgroup.com
License: UNKNOWN
Platform: UNKNOWN
Classifier: Development Status :: 3 - Alpha
Classifier: Operating System :: MacOS
Classifier: Operating System :: POSIX :: Linux
Classifier: Topic :: System :: Software Distribution
Classifier: License :: OSI Approved :: MIT License
Classifier: Programming Language :: Python
Classifier: Programming Language :: Python :: 3
Classifier: Programming Language :: Python :: 3.5
